{"id":"vertcoin","symbol":"vtc","name":"Vertcoin","localization":{"en":"Vertcoin","de":"Vertcoin","es":"Vertcoin","fr":"Vertcoin","it":"Vertcoin","pl":"Vertcoin","ro":"Vertcoin","hu":"Vertcoin","nl":"Vertcoin","pt":"Vertcoin","sv":"Vertcoin","vi":"Vertcoin","tr":"Vertcoin","ru":"Vertcoin","ja":"ヴァートコイン","zh":"绿币","zh-tw":"綠幣","ko":"버트코인","ar":"Vertcoin","th":"Vertcoin","id":"Vertcoin"},"image":{"thumb":"https://assets.coingecko.com/coins/images/18/thumb/vertcoin-logo-2018.png?1547033643","small":"https://assets.coingecko.com/coins/images/18/small/vertcoin-logo-2018.png?1547033643"},"market_data":{"current_price":{"aud":null,"bdt":78.74042699878349,"bhd":0.38202375705329683,"bmd":1.013339055036,"brl":null,"btc":0.00218004,"cad":1.113346428,"chf":0.90399064668,"cny":6.286716728484,"dkk":null,"eur":0.739483084248,"gbp":0.611339243028,"hkd":7.860447927756,"idr":null,"inr":null,"jpy":104.757875455584,"krw":1067.990092800936,"ltc":0.08898122448979591,"mmk":975.4299396531976,"mxn":null,"myr":null,"ngn":165.794226804739,"nzd":null,"php":null,"pln":null,"rub":35.812658548944,"sek":6.641649258888,"sgd":1.2762662673,"twd":30.655705911696,"uah":11.74459964786724,"usd":1.013339055036,"vef":6.378435321769616,"vnd":21371.65845005647,"xag":null,"xau":null,"xdr":0.657794805408,"zar":null},"market_cap":{"aud":null,"brl":null,"btc":null,"cad":null,"chf":null,"cny":null,"dkk":null,"eur":null,"gbp":null,"hkd":null,"idr":null,"inr":null,"jpy":null,"krw":null,"mxn":null,"myr":null,"ngn":500523999.96059996,"nzd":null,"php":null,"pln":null,"rub":null,"sek":null,"sgd":null,"twd":null,"uah":35456325.03,"usd":3059217.0,"vnd":64519906267.980255,"xag":null,"xau":null,"xdr":null,"zar":null},"total_volume":{"aud":24881.201868832344,"brl":51856.41324629538,"btc":49.7325641991452,"cad":null,"chf":20622.453198766943,"cny":null,"dkk":125928.24356219484,"eur":null,"gbp":null,"hkd":null,"idr":261669606.60416088,"inr":1387451.051629212,"jpy":null,"krw":null,"ltc":2029.900579556947,"mxn":301031.9073533247,"myr":75782.4912731703,"ngn":4017978.5843999996,"nzd":26888.935325090355,"php":1039089.0408950486,"pln":70226.85657997095,"rub":null,"sek":null,"sgd":null,"twd":699338.9398008919,"uah":284627.22,"usd":24558.0,"vnd":517936405.99181396,"xag":1159.0223819174987,"xau":17.73463239341518,"xdr":15006.065205141917,"zar":244333.35261936943}},"community_data":{"facebook_likes":null,"twitter_followers":29551,"reddit_average_posts_48h":0.0,"reddit_average_comments_48h":0.0,"reddit_subscribers":null,"reddit_accounts_active_48h":null},"developer_data":{"forks":28,"stars":41,"subscribers":19,"total_issues":14,"closed_issues":13,"pull_requests_merged":null,"pull_request_contributors":null,"code_additions_deletions_4_weeks":{"additions":null,"deletions":null},"commit_count_4_weeks":null},"public_interest_stats":{"alexa_rank":null,"bing_matches":null}}